pmb/__init__.py
pmb/aportgen/__init__.py
pmb/aportgen/binutils.py
pmb/aportgen/busybox_static.py
pmb/aportgen/core.py
pmb/aportgen/device.py
pmb/aportgen/gcc.py
pmb/aportgen/grub_efi.py
pmb/aportgen/linux.py
pmb/aportgen/musl.py
pmb/build/__init__.py
pmb/build/_package.py
pmb/build/autodetect.py
pmb/build/checksum.py
pmb/build/envkernel.py
pmb/build/init.py
pmb/build/kconfig.py
pmb/build/menuconfig.py
pmb/build/newapkbuild.py
pmb/build/other.py
pmb/build/qemu_workaround_aarch64.py
pmb/chroot/__init__.py
pmb/chroot/apk.py
pmb/chroot/apk_static.py
pmb/chroot/binfmt.py
pmb/chroot/distccd.py
pmb/chroot/init.py
pmb/chroot/initfs.py
pmb/chroot/initfs_hooks.py
pmb/chroot/mount.py
pmb/chroot/other.py
pmb/chroot/root.py
pmb/chroot/shutdown.py
pmb/chroot/user.py
pmb/chroot/zap.py
pmb/ci/__init__.py
pmb/config/__init__.py
pmb/config/init.py
pmb/config/load.py
pmb/config/merge_with_args.py
pmb/config/pmaports.py
pmb/config/save.py
pmb/config/sudo.py
pmb/config/workdir.py
pmb/data/locales
pmb/data/qemu-user-binfmt.txt
pmb/data/keys/README
pmb/data/keys/alpine-devel@lists.alpinelinux.org-4a6a0840.rsa.pub
pmb/data/keys/alpine-devel@lists.alpinelinux.org-5243ef4b.rsa.pub
pmb/data/keys/alpine-devel@lists.alpinelinux.org-524d27bb.rsa.pub
pmb/data/keys/alpine-devel@lists.alpinelinux.org-5261cecb.rsa.pub
pmb/data/keys/alpine-devel@lists.alpinelinux.org-58199dcc.rsa.pub
pmb/data/keys/alpine-devel@lists.alpinelinux.org-58cbb476.rsa.pub
pmb/data/keys/alpine-devel@lists.alpinelinux.org-58e4f17d.rsa.pub
pmb/data/keys/alpine-devel@lists.alpinelinux.org-5e69ca50.rsa.pub
pmb/data/keys/alpine-devel@lists.alpinelinux.org-60ac2099.rsa.pub
pmb/data/keys/alpine-devel@lists.alpinelinux.org-6165ee59.rsa.pub
pmb/data/keys/alpine-devel@lists.alpinelinux.org-61666e3f.rsa.pub
pmb/data/keys/alpine-devel@lists.alpinelinux.org-616a9724.rsa.pub
pmb/data/keys/alpine-devel@lists.alpinelinux.org-616abc23.rsa.pub
pmb/data/keys/alpine-devel@lists.alpinelinux.org-616ac3bc.rsa.pub
pmbootstrap-2.1.0.dist-info/LICENSE
pmbootstrap-2.1.0.dist-info/METADATA
pmbootstrap-2.1.0.dist-info/WHEEL
pmbootstrap-2.1.0.dist-info/entry_points.txt
pmbootstrap-2.1.0.dist-info/top_level.txt
pmbootstrap-2.1.0.dist-info/RECORD
