Metadata-Version: 2.1
Name: pmbootstrap
Version: 2.1.0
Summary: A sophisticated chroot / build / flash tool to develop and install postmarketOS
Home-page: https://www.postmarketos.org
Author: postmarketOS Developers
Author-email: info@postmarketos.org
License: GPLv3
Keywords: postmarketos pmbootstrap
Classifier: Development Status :: 5 - Production/Stable
Classifier: Intended Audience :: Developers
Classifier: License :: OSI Approved :: GNU General Public License v3 (GPLv3)
Classifier: Programming Language :: Python :: 3
Classifier: Programming Language :: Python :: 3.7
Classifier: Programming Language :: Python :: 3.8
Classifier: Programming Language :: Python :: 3.9
Classifier: Programming Language :: Python :: 3.10
Classifier: Programming Language :: Python :: 3.11
Requires-Python: >=3.7
License-File: LICENSE
Provides-Extra: completion
Requires-Dist: argcomplete ; extra == 'completion'
